libtorrentx/__init__.py
libtorrentx/__main__.py
libtorrentx/callback.py
libtorrentx/handle.py
libtorrentx/magnet.py
libtorrentx/session.py
libtorrentx-0.0.8.dist-info/licenses/LICENSE.txt
libtorrentx-0.0.8.dist-info/METADATA
libtorrentx-0.0.8.dist-info/WHEEL
libtorrentx-0.0.8.dist-info/entry_points.txt
libtorrentx-0.0.8.dist-info/top_level.txt
libtorrentx-0.0.8.dist-info/RECORD
