Metadata-Version: 2.4
Name: libtorrentx
Version: 0.0.8
Summary: libtorrent python api
Home-page: https://github.com/imneonizer/libtorrentx
Author: Nitin Rai
Author-email: mneonizer@gmail.com
License: MIT License
Platform: linux
Platform: unix
Requires-Python: >3.5.2
License-File: LICENSE.txt
Requires-Dist: libtorrent>=2.0.7
Dynamic: author
Dynamic: author-email
Dynamic: description
Dynamic: description-content-type
Dynamic: home-page
Dynamic: license
Dynamic: license-file
Dynamic: platform
Dynamic: requires-dist
Dynamic: requires-python
Dynamic: summary
